{
  "course_code": "UE25EE141A",
  "unit_title": "UNIT 3 : THREE PHASE BALANCED SYSTEMS & ELECTRICAL INSTALLATIONS",
  "videos": [
    {
      "title": " Domestic Tariff structure and calculation",
      "provider": "vimeo",
      "video_id": "478352268",
      "video_url": "https://player.vimeo.com/video/478352268?autoplay=0&loop=1&autopause=0&quality=240p",
      "embed_url": "https://player.vimeo.com/video/478352268",
      "faculty": "Mrs Jyothi T.N",
      "date": "05/10/2025 12:19 AM",
      "section": "NA"
    }
  ],
  "updated_at": "2026-01-22T20:47:20.916381"
}